lhachimi/__init__.py
lhachimi-0.1.2025.dist-info/METADATA
lhachimi-0.1.2025.dist-info/WHEEL
lhachimi-0.1.2025.dist-info/top_level.txt
lhachimi-0.1.2025.dist-info/RECORD
