Metadata-Version: 2.1
Name: lhachimi
Version: 0.1.2025
Summary: A basic science package
Home-page: UNKNOWN
Author: Mohamed Lhachimi
Author-email: mohamedyoutu123@gmail.com
License: UNKNOWN
Keywords: python,science,math,analysis,simplify science,programming
Platform: UNKNOWN
Classifier: Development Status :: 1 - Planning
Classifier: Intended Audience :: Developers
Classifier: Programming Language :: Python :: 3
Classifier: Operating System :: Unix
Classifier: Operating System :: MacOS :: MacOS X
Classifier: Operating System :: Microsoft :: Windows
Requires-Dist: numpy
Requires-Dist: matplotlib
Requires-Dist: sympy
Requires-Dist: scipy
Requires-Dist: scikit-learn
